<?xml version="1.0" encoding="utf-8" ?>
<Defs>

  <DanceOfEvolution.DialogueNodeDef>
    <defName>DE_MycelyssEnvoy_Root</defName>
    <text>The envoy stares at your people with dead, empty eyes and speaks in a monotone voice that almost sounds like a low, mechanical growl. "We are the Mycelyss, we have taken notice of the psychic emanations of this colony as a sign that more live here. This mycelyss colony is underdevelopped and weak. We are established and strong. It is in your best interest to become a symbiote of us. You will be assimilated into a stronger organism. Comply now."</text>
    <options>
      <li>
        <text>Of course.</text>
        <nextNode>DE_MycelyssEnvoy_ExplainDeal</nextNode>
      </li>
      <li>
        <text>Ridiculous, we would never submit to the likes of you!</text>
        <nextNode>DE_MycelyssEnvoy_Attack</nextNode>
        <outcomes>
          <li Class="DanceOfEvolution.DialogueOutcome_MakeHostile" />
        </outcomes>
      </li>
      <li>
        <text>Your colony is weaker than ours, join us or be consumed. Comply now.</text>
        <nextNode>DE_MycelyssEnvoy_Leave</nextNode>
        <outcomes>
          <li Class="DanceOfEvolution.DialogueOutcome_LeaveAndBecomeHostile" />
        </outcomes>
      </li>
    </options>
  </DanceOfEvolution.DialogueNodeDef>

  <DanceOfEvolution.DialogueNodeDef>
    <defName>DE_MycelyssEnvoy_ExplainDeal</defName>
    <text>"Affirmative. Our collective is in need of living humans for processing. Give us 2 immediately. Noncompliance will be considered rebellion and will be dealt with swiftly. Comply now."</text>
    <options>
      <li>
        <text>Accept</text>
        <outcomes>
          <li Class="DanceOfEvolution.DialogueOutcome_OpenPawnSelectWindow" />
        </outcomes>
      </li>
      <li>
        <text>Back</text>
        <outcomes>
          <li Class="DanceOfEvolution.DialogueOutcome_BackToRoot" />
        </outcomes>
      </li>
    </options>
  </DanceOfEvolution.DialogueNodeDef>

  <DanceOfEvolution.DialogueNodeDef>
    <defName>DE_MycelyssEnvoy_Attack</defName>
    <text>"Then you will be consumed."</text>
    <options>
      <li>
        <text>Close</text>
        <outcomes>
          <li Class="DanceOfEvolution.DialogueOutcome_CloseUI" />
        </outcomes>
      </li>
    </options>
  </DanceOfEvolution.DialogueNodeDef>

  <DanceOfEvolution.DialogueNodeDef>
    <defName>DE_MycelyssEnvoy_Leave</defName>
    <text>"Affirmative. Your suggestion will be processed to assertain its truth. We will come to a conclusion shortly, goodbye."</text>
    <options>
      <li>
        <text>Close</text>
        <outcomes>
          <li Class="DanceOfEvolution.DialogueOutcome_CloseUI" />
        </outcomes>
      </li>
    </options>
  </DanceOfEvolution.DialogueNodeDef>

</Defs>